{
  "userAdmonitions": {
    "def": {
      "type": "def",
      "color": "126, 160, 127",
      "icon": {
        "name": "bookmark",
        "type": "font-awesome"
      },
      "command": false,
      "title": "Definició",
      "injectColor": true,
      "noTitle": false
    },
    "met": {
      "type": "met",
      "color": "143, 183, 158",
      "icon": {
        "name": "calculator",
        "type": "font-awesome"
      },
      "command": false,
      "title": "Mètode",
      "injectColor": true,
      "noTitle": false
    },
    "teor": {
      "type": "teor",
      "color": "145, 209, 122",
      "icon": {
        "name": "book",
        "type": "font-awesome"
      },
      "command": false,
      "title": "Teorema",
      "injectColor": true,
      "noTitle": false
    },
    "not": {
      "type": "not",
      "color": "180, 222, 171",
      "icon": {
        "name": "pencil-alt",
        "type": "font-awesome"
      },
      "command": false,
      "title": "Nota",
      "injectColor": true,
      "noTitle": false
    },
    "prop": {
      "type": "prop",
      "color": "99, 176, 136",
      "icon": {
        "name": "angle-double-right",
        "type": "font-awesome"
      },
      "command": false,
      "title": "Proposició",
      "injectColor": true,
      "noTitle": false
    },
    "ex": {
      "type": "ex",
      "color": "202, 160, 160",
      "icon": {
        "name": "border-all",
        "type": "font-awesome"
      },
      "command": false,
      "title": "Exemple",
      "injectColor": true,
      "noTitle": false
    }
  },
  "syntaxHighlight": true,
  "copyButton": false,
  "version": "10.3.2",
  "autoCollapse": true,
  "defaultCollapseType": "open",
  "injectColor": true,
  "parseTitles": true,
  "dropShadow": true,
  "hideEmpty": false,
  "open": {
    "admonitions": true,
    "icons": true,
    "other": true,
    "advanced": true
  },
  "icons": [
    "octicons",
    "rpg"
  ],
  "useFontAwesome": true,
  "rpgDownloadedOnce": false,
  "msDocConverted": false,
  "useSnippet": true,
  "snippetPath": "custom-admonitions.2ddd9f"
}